[
  {
    "id": 0,
    "name": "Куринное филе"
  },
  {
    "id": 1,
    "name": "Гречка"
  },
  {
    "id": 2,
    "name": "Картофель"
  },
  {
    "id": 3,
    "name": "Рис"
  },
  {
    "id": 4,
    "name": "Консервированный ананас"
  },
  {
    "id": 5,
    "name": "Сыр"
  },
  {
    "id": 6,
    "name": "Майонез"
  },
  {
    "id": 7,
    "name": "Чеснок"
  },
  {
    "id": 8,
    "name": "Соль"
  },
  {
    "id": 9,
    "name": "Огурец"
  },
  {
    "id": 10,
    "name": "Помидор"
  },
  {
    "id": 11,
    "name": "Зеленный лук"
  },
  {
    "id": 12,
    "name": "Оливковое масло"
  },
  {
    "id": 13,
    "name": "Зеленный салат"
  },
  {
    "id": 14,
    "name": "Белый хлеб"
  },
  {
    "id": 15,
    "name": "Соус цезарь"
  },
  {
    "id": 16,
    "name": "Сливочное масло"
  },
  {
    "id": 17,
    "name": "Лук репчатый"
  },
  {
    "id": 18,
    "name": "Сахар"
  },
  {
    "id": 19,
    "name": "Перец"
  },
  {
    "id": 20,
    "name": "Яйцо"
  },
  {
    "id": 21,
    "name": "Морковь"
  },
  {
    "id": 22,
    "name": "Сметана"
  },
  {
    "id": 23,
    "name": "Томатная паста"
  },
  {
    "id": 24,
    "name": "Мука"
  },
  {
    "id": 25,
    "name": "Вода"
  },
  {
    "id": 26,
    "name": "Сливки"
  },
  {
    "id": 27,
    "name": "Кефир"
  },
  {
    "id": 28,
    "name": "Укроп"
  },
  {
    "id": 29,
    "name": "Спагетти"
  },
  {
    "id": 30,
    "name": "Специи"
  }
]